LICENSE
MANIFEST.in
README.rst
setup.py
django_screener.egg-info/PKG-INFO
django_screener.egg-info/SOURCES.txt
django_screener.egg-info/dependency_links.txt
django_screener.egg-info/top_level.txt
screener/__init__.py
screener/admin.py
screener/apps.py
screener/models.py
screener/permissions.py
screener/serializers.py
screener/urls.py
screener/utils.py
screener/views.py
screener/migrations/0001_initial.py
screener/migrations/0002_auto_20160818_1110.py
screener/migrations/__init__.py
screener/tests/__init__.py
screener/tests/test_models.py
screener/tests/test_views.py