Metadata-Version: 1.1
Name: django-screener
Version: 0.2.1
Summary: Phone screen management for interviewers
Home-page: UNKNOWN
Author: Richard Leahy
Author-email: richard-james.leahy@hotmail.co.uk
License: BSD 3-Clause
Platform: UNKNOWN
Classifier: Environment :: Web Environment
Classifier: Framework :: Django
Classifier: Framework :: Django :: 1.11
Classifier: Intended Audience :: Developers
Classifier: License :: OSI Approved :: BSD License
Classifier: Operating System :: OS Independent
Classifier: Programming Language :: Python
Classifier: Programming Language :: Python :: 2.7
Classifier: Topic :: Internet :: WWW/HTTP
Classifier: Topic :: Internet :: WWW/HTTP :: Dynamic Content
